awscli_plugin_yubikeytotp/__init__.py
awscli_plugin_yubikeytotp/boto_plugin.py
awscli_plugin_yubikeytotp/commands.py
awscli_plugin_yubikeytotp/prompter.py
awscli_plugin_yubikeytotp-1.1.0.dist-info/WHEEL
awscli_plugin_yubikeytotp-1.1.0.dist-info/METADATA
awscli_plugin_yubikeytotp-1.1.0.dist-info/RECORD
