Metadata-Version: 2.1
Name: awscli-plugin-yubikeytotp
Version: 1.1.0
Summary: 
Home-page: https://github.com/tommie-lie/awscli-plugin-yubikeytotp
License: GPL-3.0-or-later
Keywords: aws,aws-cli,boto3,yubikey
Author: Thomas Liebetraut
Author-email: thomas@tommie-lie.de
Requires-Python: >=3.7,<3.10
Classifier: Environment :: Console
Classifier: Intended Audience :: Developers
Classifier: Intended Audience :: System Administrators
Classifier: License :: OSI Approved :: GNU General Public License v3 or later (GPLv3+)
Classifier: Programming Language :: Python :: 3
Classifier: Programming Language :: Python :: 3.7
Classifier: Programming Language :: Python :: 3.8
Classifier: Programming Language :: Python :: 3.9
Requires-Dist: botocore (>=1.14.14,<2.0.0)
Requires-Dist: cryptography (<3.4)
Requires-Dist: yubikey-manager (<4)
Project-URL: Documentation, https://github.com/tommie-lie/awscli-plugin-yubikeytotp/blob/master/README.md
Project-URL: Repository, https://github.com/tommie-lie/awscli-plugin-yubikeytotp
